alpaxa_quant/__about__.py
alpaxa_quant/__init__.py
alpaxa_quant/__main__.py
alpaxa_quant/config.py
alpaxa_quant/eodhd/__init__.py
alpaxa_quant/eodhd/eodhd.py
alpaxa_quant/finra/__init__.py
alpaxa_quant/finra/finra.py
alpaxa_quant/fred/__init__.py
alpaxa_quant/fred/fred.py
alpaxa_quant/insider_trades/__init__.py
alpaxa_quant/insider_trades/insider_trades.py
alpaxa_quant/tests/__init__.py
alpaxa_quant/tests/test_config.py
alpaxa_quant/tests/test_eodhd.py
alpaxa_quant/tests/test_finra.py
alpaxa_quant/tests/test_fred.py
alpaxa_quant/tests/test_insider_trades.py
alpaxa_quant/tests/test_utils.py
alpaxa_quant/utils/__init__.py
alpaxa_quant/utils/utils.py
alpaxa_quant-1.0.2.dist-info/licenses/LICENSE
alpaxa_quant-1.0.2.dist-info/METADATA
alpaxa_quant-1.0.2.dist-info/WHEEL
alpaxa_quant-1.0.2.dist-info/top_level.txt
alpaxa_quant-1.0.2.dist-info/RECORD
