Metadata-Version: 2.4
Name: alpaxa_quant
Version: 1.0.2
Summary: # AlpaxaQuant
Home-page: https://github.com/Joanmascastella/AlpaxaQuant
Author: Joan Mas Castella
Author-email: Joan Mas Castella <jmascastella@gmail.com>
License: Apache License 2.0
Project-URL: Homepage, https://github.com/Joanmascastella/AlpaxaQuant
Project-URL: Documentation, https://github.com/Joanmascastella/AlpaxaQuant#readme
Project-URL: Source, https://github.com/Joanmascastella/AlpaxaQuant
Project-URL: Issues, https://github.com/Joanmascastella/AlpaxaQuant/issues
Keywords: quantitative finance,market data,macroeconomics,EODHD,FINRA,FRED,insider trading,econometrics
Classifier: Programming Language :: Python :: 3
Classifier: License :: OSI Approved :: Apache Software License
Classifier: Operating System :: OS Independent
Classifier: Topic :: Scientific/Engineering :: Information Analysis
Classifier: Topic :: Software Development :: Libraries :: Python Modules
Requires-Python: >=3.9
License-File: LICENSE
Requires-Dist: beautifulsoup4==4.14.2
Requires-Dist: certifi==2025.10.5
Requires-Dist: cffi==2.0.0
Requires-Dist: charset-normalizer==3.4.4
Requires-Dist: curl_cffi==0.13.0
Requires-Dist: decorator==5.2.1
Requires-Dist: frozendict==2.4.6
Requires-Dist: html5lib==1.1
Requires-Dist: idna==3.11
Requires-Dist: iniconfig==2.3.0
Requires-Dist: lxml==6.0.2
Requires-Dist: multitasking==0.0.12
Requires-Dist: numpy==2.3.4
Requires-Dist: packaging==25.0
Requires-Dist: pandas==2.3.3
Requires-Dist: peewee==3.18.3
Requires-Dist: platformdirs==4.5.0
Requires-Dist: pluggy==1.6.0
Requires-Dist: protobuf==6.33.0
Requires-Dist: pycparser==2.23
Requires-Dist: Pygments==2.19.2
Requires-Dist: pytest==8.4.2
Requires-Dist: python-dateutil==2.9.0.post0
Requires-Dist: python-dotenv==1.2.1
Requires-Dist: pytz==2025.2
Requires-Dist: requests==2.32.5
Requires-Dist: retry==0.9.2
Requires-Dist: setuptools==80.9.0
Requires-Dist: six==1.17.0
Requires-Dist: soupsieve==2.8
Requires-Dist: tqdm==4.67.1
Requires-Dist: typing_extensions==4.15.0
Requires-Dist: tzdata==2025.2
Requires-Dist: urllib3==2.5.0
Requires-Dist: webencodings==0.5.1
Requires-Dist: websockets==15.0.1
Requires-Dist: yfinance==0.2.66
Dynamic: author
Dynamic: home-page
Dynamic: license-file
Dynamic: requires-python
